aws_cdk_lambdecor/__init__.py
aws_cdk_lambdecor-0.2.1.dist-info/LICENSE
aws_cdk_lambdecor-0.2.1.dist-info/METADATA
aws_cdk_lambdecor-0.2.1.dist-info/WHEEL
aws_cdk_lambdecor-0.2.1.dist-info/top_level.txt
aws_cdk_lambdecor-0.2.1.dist-info/RECORD
