Metadata-Version: 2.1
Name: aws-cdk-lambdecor
Version: 0.2.1
Summary: Define AWS CDK Lambda using native python functions
Home-page: UNKNOWN
Author: Eli Polonsky
License: LICENSE
Platform: UNKNOWN
Classifier: Framework :: AWS CDK
Classifier: Framework :: AWS CDK :: 1
Classifier: Operating System :: POSIX :: Linux
Classifier: Operating System :: Microsoft
Classifier: License :: OSI Approved :: Apache Software License
Classifier: Programming Language :: Python :: 3 :: Only
Classifier: Programming Language :: Python :: 3.6
Classifier: Programming Language :: Python :: 3.7
Classifier: Programming Language :: Python :: 3.8
Requires-Python: >=3.6
Requires-Dist: aws-cdk.core (<2.0.0,>=1.61.0)
Requires-Dist: aws-cdk.aws-lambda (<2.0.0,>=1.61.0)
Requires-Dist: aws-cdk.custom-resources (<2.0.0,>=1.61.0)
Requires-Dist: aws-cdk.aws-s3 (<2.0.0,>=1.61.0)
